[{"name": "Rome", "founding": -753, "lat": 41.8931, "lng": 12.4828}, {"name": "Athens", "founding": -1400, "lat": 37.9838, "lng": 23.7275}, {"name": "Paris", "founding": -250, "lat": 48.8566, "lng": 2.3522}, {"name": "London", "founding": 43, "lat": 51.5074, "lng": -0.1278}, {"name": "Berlin", "founding": 1237, "lat": 52.52, "lng": 13.405}, {"name": "Madrid", "founding": 860, "lat": 40.4168, "lng": -3.7038}, {"name": "Vienna", "founding": 500, "lat": 48.2082, "lng": 16.3738}, {"name": "Lisbon", "founding": 1200, "lat": 38.7223, "lng": -9.1393}, {"name": "Venice", "founding": 421, "lat": 45.4408, "lng": 12.3155}, {"name": "Moscow", "founding": 1147, "lat": 55.7558, "lng": 37.6173}, {"name": "Naples", "founding": -600, "lat": 40.8518, "lng": 14.2681}, {"name": "Istanbul", "founding": 660, "lat": 41.0082, "lng": 28.9784}, {"name": "Cologne", "founding": 50, "lat": 50.9375, "lng": 6.9603}, {"name": "Hamburg", "founding": 808, "lat": 53.5511, "lng": 9.9937}, {"name": "Florence", "founding": 59, "lat": 43.7696, "lng": 11.2558}, {"name": "Prague", "founding": 880, "lat": 50.0755, "lng": 14.4378}, {"name": "Brussels", "founding": 979, "lat": 50.8503, "lng": 4.3517}, {"name": "Copenhagen", "founding": 1167, "lat": 55.6761, "lng": 12.5683}, {"name": "Stockholm", "founding": 1252, "lat": 59.3293, "lng": 18.0686}, {"name": "Edinburgh", "founding": 850, "lat": 55.9533, "lng": -3.1883}, {"name": "Bordeaux", "founding": -300, "lat": 44.8378, "lng": -0.5792}, {"name": "Seville", "founding": -800, "lat": 37.3891, "lng": -5.9845}, {"name": "Genoa", "founding": -200, "lat": 44.4056, "lng": 8.9463}, {"name": "Lyon", "founding": -43, "lat": 45.764, "lng": 4.8357}, {"name": "Zurich", "founding": -15, "lat": 47.3769, "lng": 8.5417}, {"name": "Warsaw", "founding": 1300, "lat": 52.2297, "lng": 21.0122}, {"name": "Valencia", "founding": -138, "lat": 39.4699, "lng": -0.3763}, {"name": "Turin", "founding": -27, "lat": 45.0703, "lng": 7.6869}, {"name": "Milan", "founding": -600, "lat": 45.4642, "lng": 9.19}, {"name": "Bologna", "founding": -534, "lat": 44.4949, "lng": 11.3426}, {"name": "Belgrade", "founding": 279, "lat": 44.7866, "lng": 20.4489}, {"name": "Krakow", "founding": 700, "lat": 50.0647, "lng": 19.945}, {"name": "Oslo", "founding": 1048, "lat": 59.9139, "lng": 10.7522}, {"name": "Helsinki", "founding": 1550, "lat": 60.1695, "lng": 24.9354}, {"name": "Riga", "founding": 1201, "lat": 56.9496, "lng": 24.1052}, {"name": "Vilnius", "founding": 1323, "lat": 54.6872, "lng": 25.2797}, {"name": "Dublin", "founding": 988, "lat": 53.3498, "lng": -6.2603}, {"name": "Bucharest", "founding": 1459, "lat": 44.4268, "lng": 26.1025}, {"name": "Sarajevo", "founding": 1461, "lat": 43.8563, "lng": 18.4131}, {"name": "Lille", "founding": 1066, "lat": 50.6292, "lng": 3.0573}, {"name": "Nantes", "founding": -20, "lat": 47.2184, "lng": -1.5536}, {"name": "Bristol", "founding": 1000, "lat": 51.4545, "lng": -2.5879}, {"name": "Ghent", "founding": 650, "lat": 51.0543, "lng": 3.7174}, {"name": "Aachen", "founding": 765, "lat": 50.7753, "lng": 6.0839}, {"name": "Toulouse", "founding": -400, "lat": 43.6047, "lng": 1.4442}, {"name": "Antwerp", "founding": 1500, "lat": 51.2194, "lng": 4.4025}, {"name": "Malaga", "founding": -770, "lat": 36.7213, "lng": -4.4214}, {"name": "Barcelona", "founding": -15, "lat": 41.3851, "lng": 2.1734}, {"name": "Marseille", "founding": -600, "lat": 43.2965, "lng": 5.3698}, {"name": "Nice", "founding": -350, "lat": 43.7102, "lng": 7.262}, {"name": "Strasbourg", "founding": 12, "lat": 48.5734, "lng": 7.7521}, {"name": "Rennes", "founding": 50, "lat": 48.1173, "lng": -1.6778}, {"name": "Reims", "founding": -80, "lat": 49.2583, "lng": 4.0317}, {"name": "Dijon", "founding": 50, "lat": 47.322, "lng": 5.0415}, {"name": "Grenoble", "founding": -15, "lat": 45.1885, "lng": 5.7245}, {"name": "Avignon", "founding": -120, "lat": 43.9493, "lng": 4.8055}, {"name": "Rouen", "founding": -100, "lat": 49.4431, "lng": 1.0993}, {"name": "Orleans", "founding": -50, "lat": 47.9025, "lng": 1.909}, {"name": "Tours", "founding": -1, "lat": 47.3941, "lng": 0.6848}, {"name": "Amiens", "founding": -50, "lat": 49.8941, "lng": 2.2958}, {"name": "Metz", "founding": -300, "lat": 49.1193, "lng": 6.1757}, {"name": "Nancy", "founding": 1050, "lat": 48.6921, "lng": 6.1844}, {"name": "Munich", "founding": 1158, "lat": 48.1351, "lng": 11.582}, {"name": "Frankfurt", "founding": 794, "lat": 50.1109, "lng": 8.6821}, {"name": "Stuttgart", "founding": 950, "lat": 48.7758, "lng": 9.1829}, {"name": "Düsseldorf", "founding": 1288, "lat": 51.2277, "lng": 6.7735}, {"name": "Dresden", "founding": 1206, "lat": 51.0504, "lng": 13.7373}, {"name": "Leipzig", "founding": 1015, "lat": 51.3397, "lng": 12.3731}, {"name": "Nuremberg", "founding": 1050, "lat": 49.4521, "lng": 11.0767}, {"name": "Hannover", "founding": 1150, "lat": 52.3759, "lng": 9.732}, {"name": "Bremen", "founding": 787, "lat": 53.0793, "lng": 8.8017}, {"name": "Bonn", "founding": 1, "lat": 50.7374, "lng": 7.0982}, {"name": "Essen", "founding": 852, "lat": 51.4556, "lng": 7.0116}, {"name": "Dortmund", "founding": 882, "lat": 51.5136, "lng": 7.4653}, {"name": "Mainz", "founding": -13, "lat": 50.0, "lng": 8.2711}, {"name": "Münster", "founding": 793, "lat": 51.9607, "lng": 7.6261}, {"name": "Augsburg", "founding": -15, "lat": 48.3705, "lng": 10.8978}, {"name": "Freiburg im Breisgau", "founding": 1120, "lat": 47.999, "lng": 7.8421}, {"name": "Regensburg", "founding": 179, "lat": 49.0134, "lng": 12.1016}, {"name": "Heidelberg", "founding": 1196, "lat": 49.3988, "lng": 8.6724}, {"name": "Karlsruhe", "founding": 1715, "lat": 49.0069, "lng": 8.4037}, {"name": "Wiesbaden", "founding": 6, "lat": 50.0782, "lng": 8.2398}, {"name": "Mannheim", "founding": 1607, "lat": 49.4875, "lng": 8.466}, {"name": "Kiel", "founding": 1242, "lat": 54.3233, "lng": 10.1228}, {"name": "Lübeck", "founding": 1143, "lat": 53.8655, "lng": 10.6866}, {"name": "Erfurt", "founding": 742, "lat": 50.9848, "lng": 11.0299}, {"name": "Magdeburg", "founding": 805, "lat": 52.1205, "lng": 11.6276}, {"name": "Rostock", "founding": 1218, "lat": 54.0924, "lng": 12.0991}, {"name": "Amsterdam", "founding": 1275, "lat": 52.3676, "lng": 4.9041}, {"name": "Rotterdam", "founding": 1340, "lat": 51.9244, "lng": 4.4777}, {"name": "The Hague", "founding": 1230, "lat": 52.0705, "lng": 4.3007}, {"name": "Utrecht", "founding": 50, "lat": 52.0907, "lng": 5.1214}, {"name": "Leiden", "founding": 860, "lat": 52.1601, "lng": 4.497}, {"name": "Haarlem", "founding": 1245, "lat": 52.3874, "lng": 4.6462}, {"name": "Bruges", "founding": 1128, "lat": 51.2093, "lng": 3.2247}, {"name": "Leuven", "founding": 891, "lat": 50.8798, "lng": 4.7005}, {"name": "Liège", "founding": 705, "lat": 50.6326, "lng": 5.5797}, {"name": "Namur", "founding": 907, "lat": 50.4674, "lng": 4.8718}, {"name": "Mons", "founding": 800, "lat": 50.4542, "lng": 3.95}, {"name": "Luxembourg City", "founding": 963, "lat": 49.6116, "lng": 6.1319}, {"name": "Geneva", "founding": -120, "lat": 46.2044, "lng": 6.1432}, {"name": "Basel", "founding": -44, "lat": 47.5596, "lng": 7.5886}, {"name": "Bern", "founding": 1191, "lat": 46.948, "lng": 7.4474}, {"name": "Lausanne", "founding": -15, "lat": 46.5197, "lng": 6.6323}, {"name": "Lucerne", "founding": 1178, "lat": 47.0502, "lng": 8.3093}, {"name": "St. Gallen", "founding": 719, "lat": 47.4245, "lng": 9.3767}, {"name": "Trieste", "founding": -178, "lat": 45.6495, "lng": 13.7768}, {"name": "Verona", "founding": -89, "lat": 45.4384, "lng": 10.9916}, {"name": "Padua", "founding": -300, "lat": 45.4064, "lng": 11.8768}, {"name": "Parma", "founding": -183, "lat": 44.8015, "lng": 10.3279}, {"name": "Modena", "founding": -183, "lat": 44.6471, "lng": 10.9252}, {"name": "Pisa", "founding": -600, "lat": 43.716, "lng": 10.3966}, {"name": "Siena", "founding": -400, "lat": 43.3188, "lng": 11.3306}, {"name": "Perugia", "founding": -310, "lat": 43.1107, "lng": 12.3908}, {"name": "Ferrara", "founding": 753, "lat": 44.8381, "lng": 11.6198}, {"name": "Bergamo", "founding": -196, "lat": 45.6983, "lng": 9.6773}, {"name": "Brescia", "founding": -200, "lat": 45.5416, "lng": 10.2118}, {"name": "Palermo", "founding": -734, "lat": 38.1157, "lng": 13.3613}, {"name": "Catania", "founding": -729, "lat": 37.5079, "lng": 15.083}, {"name": "Bari", "founding": -181, "lat": 41.1171, "lng": 16.8719}, {"name": "Cagliari", "founding": -800, "lat": 39.2238, "lng": 9.1217}, {"name": "Taranto", "founding": -706, "lat": 40.4644, "lng": 17.247}, {"name": "Lecce", "founding": -200, "lat": 40.3515, "lng": 18.175}, {"name": "Udine", "founding": 983, "lat": 46.062, "lng": 13.234}, {"name": "Zaragoza", "founding": -25, "lat": 41.6518, "lng": -0.8818}, {"name": "Bilbao", "founding": 1300, "lat": 43.263, "lng": -2.935}, {"name": "San Sebastián", "founding": 1180, "lat": 43.3183, "lng": -1.9812}, {"name": "Salamanca", "founding": -300, "lat": 40.9701, "lng": -5.6635}, {"name": "Valladolid", "founding": 1072, "lat": 41.6523, "lng": -4.7245}, {"name": "Burgos", "founding": 884, "lat": 42.3439, "lng": -3.6969}, {"name": "León", "founding": 74, "lat": 42.5987, "lng": -5.5671}, {"name": "Córdoba", "founding": -206, "lat": 37.8882, "lng": -4.7794}, {"name": "Granada", "founding": 1013, "lat": 37.1773, "lng": -3.5986}, {"name": "Alicante", "founding": -324, "lat": 38.3452, "lng": -0.481}, {"name": "Murcia", "founding": 825, "lat": 37.9847, "lng": -1.128}, {"name": "Pamplona", "founding": -75, "lat": 42.8125, "lng": -1.6458}, {"name": "Santiago de Compostela", "founding": 829, "lat": 42.8806, "lng": -8.5456}, {"name": "A Coruña", "founding": 1208, "lat": 43.3623, "lng": -8.4115}, {"name": "Gijón", "founding": -500, "lat": 43.5322, "lng": -5.6611}, {"name": "Oviedo", "founding": 761, "lat": 43.3619, "lng": -5.8494}, {"name": "Toledo", "founding": -192, "lat": 39.8628, "lng": -4.0273}, {"name": "Tarragona", "founding": -218, "lat": 41.1189, "lng": 1.2445}, {"name": "Manchester", "founding": 79, "lat": 53.4808, "lng": -2.2426}, {"name": "Birmingham", "founding": 1166, "lat": 52.4862, "lng": -1.8904}, {"name": "Liverpool", "founding": 1207, "lat": 53.4084, "lng": -2.9916}, {"name": "Leeds", "founding": 1207, "lat": 53.8008, "lng": -1.5491}, {"name": "Sheffield", "founding": 1296, "lat": 53.3811, "lng": -1.4701}]